more.chameleon-0.2-py2.7-nspkg.pth
more/chameleon/__init__.py
more/chameleon/main.py
more/chameleon/tests/__init__.py
more/chameleon/tests/test_chameleon.py
more/chameleon/tests/fixtures/__init__.py
more/chameleon/tests/fixtures/override_template.py
more/chameleon/tests/fixtures/override_template_loader.py
more/chameleon/tests/fixtures/template.py
more/chameleon/tests/fixtures/template_macro.py
more.chameleon-0.2.dist-info/DESCRIPTION.rst
more.chameleon-0.2.dist-info/METADATA
more.chameleon-0.2.dist-info/metadata.json
more.chameleon-0.2.dist-info/namespace_packages.txt
more.chameleon-0.2.dist-info/RECORD
more.chameleon-0.2.dist-info/top_level.txt
more.chameleon-0.2.dist-info/WHEEL
