Metadata-Version: 2.0
Name: more.chameleon
Version: 0.2
Summary: Chameleon template integration for Morepath
Home-page: http://pypi.python.org/pypi/more.chameleon
Author: Martijn Faassen
Author-email: faassen@startifact.com
License: BSD
Keywords: morepath chameleon
Platform: UNKNOWN
Requires-Dist: setuptools
Requires-Dist: morepath (>=0.10)
Requires-Dist: chameleon (>=2.20)
Provides-Extra: test
Requires-Dist: pytest (>=2.6.0); extra == 'test'
Requires-Dist: pytest-cov; extra == 'test'
Requires-Dist: WebTest; extra == 'test'
